backquotes.py
backquotes-0.0.3.dist-info/METADATA
backquotes-0.0.3.dist-info/WHEEL
backquotes-0.0.3.dist-info/RECORD
backquotes-0.0.3.dist-info/metadata.json
backquotes-0.0.3.dist-info/top_level.txt
backquotes-0.0.3.dist-info/DESCRIPTION.rst
