Metadata-Version: 2.0
Name: backquotes
Version: 0.0.3
Summary: shell command invocation with backquotes, like Perl, Ruby.
Home-page: https://github.com/manicmaniac/backquotes
Author: Ryosuke Ito
Author-email: rito.0305@gmail.com
License: UNKNOWN
Keywords: backquote shell syntax perl ruby sh bash
Platform: UNKNOWN
Classifier: Development Status :: 3 - Alpha
Classifier: Topic :: System :: Shells
Classifier: Topic :: Utilities
Classifier: Programming Language :: Python :: 2
Classifier: Programming Language :: Python :: 2.6
Classifier: Programming Language :: Python :: 2.7
Classifier: Programming Language :: Python :: 3
Classifier: Programming Language :: Python :: 3.2
Classifier: Programming Language :: Python :: 3.3
Classifier: Programming Language :: Python :: 3.4
Classifier: Programming Language :: Python :: 3.5
Classifier: Operating System :: OS Independent
Classifier: License :: OSI Approved :: MIT License
